LICENSE
MANIFEST.in
README.md
requirements.txt
setup.py
laser_range_finder/__init__.py
laser_range_finder/laser_range_finder.py
laser_range_finder/utils.py
laser_range_finder.egg-info/PKG-INFO
laser_range_finder.egg-info/SOURCES.txt
laser_range_finder.egg-info/dependency_links.txt
laser_range_finder.egg-info/requires.txt
laser_range_finder.egg-info/top_level.txt
laser_range_finder.egg-info/zip-safe
laser_range_finder/tests/__init__.py
laser_range_finder/tests/test_distance.py