Metadata-Version: 1.1
Name: laser-range-finder
Version: 0.1.0
Summary: Calculates distance using images taken with a generic webcam and a low-power laser
Home-page: https://github.com/chrisspen/laser_range_finder
Author: Chris Spencer
Author-email: chrisspen@gmail.com
License: MIT License
Platform: OS Independent
Classifier: Programming Language :: Python
Classifier: Programming Language :: Python :: 2.7
Classifier: Programming Language :: Python :: 3.2
Classifier: License :: OSI Approved :: MIT License
Classifier: Operating System :: OS Independent
Classifier: Topic :: Software Development :: Libraries :: Python Modules
